{"installedGatsbyVersion":"3.2.1","dependencies":["gatsby@^3.2.1","gatsby-plugin-gatsby-cloud@^2.2.0","gatsby-plugin-image@^1.2.1","gatsby-plugin-manifest@^3.2.0","gatsby-plugin-offline@^4.2.0","gatsby-plugin-postcss@^4.2.0","gatsby-plugin-react-helmet@^4.2.0","gatsby-plugin-sharp@^3.2.1","gatsby-source-filesystem@^3.2.0","gatsby-transformer-sharp@^3.2.0","prop-types@^15.7.2","react@^17.0.1","react-dom@^17.0.1","react-helmet@^6.1.0"],"devDependencies":["node-sass@^5.0.0","prettier@2.2.1","tailwindcss@^2.1.1"],"eventType":"CLI_COMMAND_METADATA","sessionId":"f2c5a479-a8ca-408b-a4ef-492bda8591f9","time":"2021-04-07T22:39:42.903Z","machineId":"c48bc250-dd69-4dcb-87c6-aa73be888b8a","componentId":"gatsby-cli","osInformation":{"nodeVersion":"v15.14.0","platform":"linux","release":"5.11.13-arch1-1","cpus":"11th Gen Intel(R) Core(TM) i5-1135G7 @ 2.40GHz","arch":"x64","ci":false,"ciName":null,"docker":false,"termProgram":"tmux","isTTY":true},"componentVersion":"2.2.0","dbEngine":"redux","features":[],"repositoryId":"git:922532e2e902cbe3de09d9d12bd4063122c43df9ebf3a0f55b11b7f6fdc5ebee","repositoryData":{"provider":"3aeb002460381c6f258e8395d3026f571f0d9a76488dcd837639b13aed316560","owner":"4802165693016e28eb2e0a119d108943ea3e918af9b11e5caa073607c0bb8edd","name":"f79ad80b94f6b8e16bdcc8c42e023f768754b0b83db96253b4132d3f12081a13"}}
{"installedGatsbyVersion":"3.2.1","gatsbyCliVersion":"3.2.0","siteHash":"a887cd0a0718944fe3448416e45fdd3a","eventType":"CLI_RAW_COMMAND_DEVELOP","sessionId":"f2c5a479-a8ca-408b-a4ef-492bda8591f9","time":"2021-04-07T22:39:43.625Z","machineId":"c48bc250-dd69-4dcb-87c6-aa73be888b8a","componentId":"gatsby-cli","osInformation":{"nodeVersion":"v15.14.0","platform":"linux","release":"5.11.13-arch1-1","cpus":"11th Gen Intel(R) Core(TM) i5-1135G7 @ 2.40GHz","arch":"x64","ci":false,"ciName":null,"docker":false,"termProgram":"tmux","isTTY":true},"componentVersion":"2.2.0","dbEngine":"redux","features":[],"repositoryId":"git:922532e2e902cbe3de09d9d12bd4063122c43df9ebf3a0f55b11b7f6fdc5ebee","repositoryData":{"provider":"3aeb002460381c6f258e8395d3026f571f0d9a76488dcd837639b13aed316560","owner":"4802165693016e28eb2e0a119d108943ea3e918af9b11e5caa073607c0bb8edd","name":"f79ad80b94f6b8e16bdcc8c42e023f768754b0b83db96253b4132d3f12081a13"}}
{"installedGatsbyVersion":"3.2.1","gatsbyCliVersion":"-0.0.0","dependencies":["gatsby@^3.2.1","gatsby-plugin-gatsby-cloud@^2.2.0","gatsby-plugin-image@^1.2.1","gatsby-plugin-manifest@^3.2.0","gatsby-plugin-offline@^4.2.0","gatsby-plugin-postcss@^4.2.0","gatsby-plugin-react-helmet@^4.2.0","gatsby-plugin-sharp@^3.2.1","gatsby-source-filesystem@^3.2.0","gatsby-transformer-sharp@^3.2.0","prop-types@^15.7.2","react@^17.0.1","react-dom@^17.0.1","react-helmet@^6.1.0"],"devDependencies":["node-sass@^5.0.0","prettier@2.2.1","tailwindcss@^2.1.1"],"eventType":"CLI_COMMAND_METADATA","sessionId":"f2c5a479-a8ca-408b-a4ef-492bda8591f9","time":"2021-04-07T22:39:43.876Z","machineId":"c48bc250-dd69-4dcb-87c6-aa73be888b8a","componentId":"gatsby-cli","osInformation":{"nodeVersion":"v15.14.0","platform":"linux","release":"5.11.13-arch1-1","cpus":"11th Gen Intel(R) Core(TM) i5-1135G7 @ 2.40GHz","arch":"x64","ci":false,"ciName":null,"docker":false,"termProgram":"tmux","isTTY":true},"componentVersion":"2.2.0","dbEngine":"redux","features":[],"repositoryId":"git:922532e2e902cbe3de09d9d12bd4063122c43df9ebf3a0f55b11b7f6fdc5ebee","repositoryData":{"provider":"3aeb002460381c6f258e8395d3026f571f0d9a76488dcd837639b13aed316560","owner":"4802165693016e28eb2e0a119d108943ea3e918af9b11e5caa073607c0bb8edd","name":"f79ad80b94f6b8e16bdcc8c42e023f768754b0b83db96253b4132d3f12081a13"}}
{"installedGatsbyVersion":"3.2.1","gatsbyCliVersion":"-0.0.0","dependencies":["gatsby@^3.2.1","gatsby-plugin-gatsby-cloud@^2.2.0","gatsby-plugin-image@^1.2.1","gatsby-plugin-manifest@^3.2.0","gatsby-plugin-offline@^4.2.0","gatsby-plugin-postcss@^4.2.0","gatsby-plugin-react-helmet@^4.2.0","gatsby-plugin-sharp@^3.2.1","gatsby-source-filesystem@^3.2.0","gatsby-transformer-sharp@^3.2.0","prop-types@^15.7.2","react@^17.0.1","react-dom@^17.0.1","react-helmet@^6.1.0"],"devDependencies":["node-sass@^5.0.0","prettier@2.2.1","tailwindcss@^2.1.1"],"eventType":"CLI_COMMAND_METADATA","sessionId":"f2c5a479-a8ca-408b-a4ef-492bda8591f9","time":"2021-04-07T22:39:44.296Z","machineId":"c48bc250-dd69-4dcb-87c6-aa73be888b8a","componentId":"gatsby-cli","osInformation":{"nodeVersion":"v15.14.0","platform":"linux","release":"5.11.13-arch1-1","cpus":"11th Gen Intel(R) Core(TM) i5-1135G7 @ 2.40GHz","arch":"x64","ci":false,"ciName":null,"docker":false,"termProgram":"tmux","isTTY":true},"componentVersion":"2.2.0","dbEngine":"redux","features":[],"repositoryId":"git:922532e2e902cbe3de09d9d12bd4063122c43df9ebf3a0f55b11b7f6fdc5ebee","repositoryData":{"provider":"3aeb002460381c6f258e8395d3026f571f0d9a76488dcd837639b13aed316560","owner":"4802165693016e28eb2e0a119d108943ea3e918af9b11e5caa073607c0bb8edd","name":"f79ad80b94f6b8e16bdcc8c42e023f768754b0b83db96253b4132d3f12081a13"}}
{"installedGatsbyVersion":"3.2.1","gatsbyCliVersion":"-0.0.0","dependencies":["gatsby@^3.2.1","gatsby-plugin-gatsby-cloud@^2.2.0","gatsby-plugin-image@^1.2.1","gatsby-plugin-manifest@^3.2.0","gatsby-plugin-offline@^4.2.0","gatsby-plugin-postcss@^4.2.0","gatsby-plugin-react-helmet@^4.2.0","gatsby-plugin-sharp@^3.2.1","gatsby-source-filesystem@^3.2.0","gatsby-transformer-sharp@^3.2.0","prop-types@^15.7.2","react@^17.0.1","react-dom@^17.0.1","react-helmet@^6.1.0"],"devDependencies":["node-sass@^5.0.0","prettier@2.2.1","tailwindcss@^2.1.1"],"eventType":"CLI_COMMAND_METADATA","sessionId":"f2c5a479-a8ca-408b-a4ef-492bda8591f9","time":"2021-04-07T22:39:44.307Z","machineId":"c48bc250-dd69-4dcb-87c6-aa73be888b8a","componentId":"gatsby-cli","osInformation":{"nodeVersion":"v15.14.0","platform":"linux","release":"5.11.13-arch1-1","cpus":"11th Gen Intel(R) Core(TM) i5-1135G7 @ 2.40GHz","arch":"x64","ci":false,"ciName":null,"docker":false,"termProgram":"tmux","isTTY":true},"componentVersion":"2.2.0","dbEngine":"redux","features":[],"repositoryId":"git:922532e2e902cbe3de09d9d12bd4063122c43df9ebf3a0f55b11b7f6fdc5ebee","repositoryData":{"provider":"3aeb002460381c6f258e8395d3026f571f0d9a76488dcd837639b13aed316560","owner":"4802165693016e28eb2e0a119d108943ea3e918af9b11e5caa073607c0bb8edd","name":"f79ad80b94f6b8e16bdcc8c42e023f768754b0b83db96253b4132d3f12081a13"}}
{"installedGatsbyVersion":"3.2.1","gatsbyCliVersion":"-0.0.0","siteHash":"a887cd0a0718944fe3448416e45fdd3a","eventType":"CLI_COMMAND_DEVELOP_START","sessionId":"f2c5a479-a8ca-408b-a4ef-492bda8591f9","time":"2021-04-07T22:39:45.543Z","machineId":"c48bc250-dd69-4dcb-87c6-aa73be888b8a","componentId":"gatsby-cli","osInformation":{"nodeVersion":"v15.14.0","platform":"linux","release":"5.11.13-arch1-1","cpus":"11th Gen Intel(R) Core(TM) i5-1135G7 @ 2.40GHz","arch":"x64","ci":false,"ciName":null,"docker":false,"termProgram":"tmux","isTTY":true},"componentVersion":"2.2.0","dbEngine":"redux","features":[],"repositoryId":"git:922532e2e902cbe3de09d9d12bd4063122c43df9ebf3a0f55b11b7f6fdc5ebee","repositoryData":{"provider":"3aeb002460381c6f258e8395d3026f571f0d9a76488dcd837639b13aed316560","owner":"4802165693016e28eb2e0a119d108943ea3e918af9b11e5caa073607c0bb8edd","name":"f79ad80b94f6b8e16bdcc8c42e023f768754b0b83db96253b4132d3f12081a13"}}
{"installedGatsbyVersion":"3.2.1","gatsbyCliVersion":"-0.0.0","name":"open and validate gatsby-configs","duration":34,"siteHash":"a887cd0a0718944fe3448416e45fdd3a","eventType":"CLI_COMMAND_ACTIVITY_DURATION","sessionId":"f2c5a479-a8ca-408b-a4ef-492bda8591f9","time":"2021-04-07T22:39:45.587Z","machineId":"c48bc250-dd69-4dcb-87c6-aa73be888b8a","componentId":"gatsby-cli","osInformation":{"nodeVersion":"v15.14.0","platform":"linux","release":"5.11.13-arch1-1","cpus":"11th Gen Intel(R) Core(TM) i5-1135G7 @ 2.40GHz","arch":"x64","ci":false,"ciName":null,"docker":false,"termProgram":"tmux","isTTY":true},"componentVersion":"2.2.0","dbEngine":"redux","features":[],"repositoryId":"git:922532e2e902cbe3de09d9d12bd4063122c43df9ebf3a0f55b11b7f6fdc5ebee","repositoryData":{"provider":"3aeb002460381c6f258e8395d3026f571f0d9a76488dcd837639b13aed316560","owner":"4802165693016e28eb2e0a119d108943ea3e918af9b11e5caa073607c0bb8edd","name":"f79ad80b94f6b8e16bdcc8c42e023f768754b0b83db96253b4132d3f12081a13"}}
{"installedGatsbyVersion":"3.2.1","gatsbyCliVersion":"-0.0.0","name":"load plugins","duration":400,"siteHash":"a887cd0a0718944fe3448416e45fdd3a","eventType":"CLI_COMMAND_ACTIVITY_DURATION","sessionId":"f2c5a479-a8ca-408b-a4ef-492bda8591f9","time":"2021-04-07T22:39:45.996Z","machineId":"c48bc250-dd69-4dcb-87c6-aa73be888b8a","componentId":"gatsby-cli","osInformation":{"nodeVersion":"v15.14.0","platform":"linux","release":"5.11.13-arch1-1","cpus":"11th Gen Intel(R) Core(TM) i5-1135G7 @ 2.40GHz","arch":"x64","ci":false,"ciName":null,"docker":false,"termProgram":"tmux","isTTY":true},"componentVersion":"2.2.0","dbEngine":"redux","features":[],"repositoryId":"git:922532e2e902cbe3de09d9d12bd4063122c43df9ebf3a0f55b11b7f6fdc5ebee","repositoryData":{"provider":"3aeb002460381c6f258e8395d3026f571f0d9a76488dcd837639b13aed316560","owner":"4802165693016e28eb2e0a119d108943ea3e918af9b11e5caa073607c0bb8edd","name":"f79ad80b94f6b8e16bdcc8c42e023f768754b0b83db96253b4132d3f12081a13"}}
{"installedGatsbyVersion":"3.2.1","gatsbyCliVersion":"-0.0.0","name":"onPreInit","duration":37,"siteHash":"a887cd0a0718944fe3448416e45fdd3a","eventType":"CLI_COMMAND_ACTIVITY_DURATION","sessionId":"f2c5a479-a8ca-408b-a4ef-492bda8591f9","time":"2021-04-07T22:39:46.036Z","machineId":"c48bc250-dd69-4dcb-87c6-aa73be888b8a","componentId":"gatsby-cli","osInformation":{"nodeVersion":"v15.14.0","platform":"linux","release":"5.11.13-arch1-1","cpus":"11th Gen Intel(R) Core(TM) i5-1135G7 @ 2.40GHz","arch":"x64","ci":false,"ciName":null,"docker":false,"termProgram":"tmux","isTTY":true},"componentVersion":"2.2.0","dbEngine":"redux","features":[],"repositoryId":"git:922532e2e902cbe3de09d9d12bd4063122c43df9ebf3a0f55b11b7f6fdc5ebee","repositoryData":{"provider":"3aeb002460381c6f258e8395d3026f571f0d9a76488dcd837639b13aed316560","owner":"4802165693016e28eb2e0a119d108943ea3e918af9b11e5caa073607c0bb8edd","name":"f79ad80b94f6b8e16bdcc8c42e023f768754b0b83db96253b4132d3f12081a13"}}
{"installedGatsbyVersion":"3.2.1","gatsbyCliVersion":"-0.0.0","name":"initialize cache","duration":14,"siteHash":"a887cd0a0718944fe3448416e45fdd3a","eventType":"CLI_COMMAND_ACTIVITY_DURATION","sessionId":"f2c5a479-a8ca-408b-a4ef-492bda8591f9","time":"2021-04-07T22:39:46.052Z","machineId":"c48bc250-dd69-4dcb-87c6-aa73be888b8a","componentId":"gatsby-cli","osInformation":{"nodeVersion":"v15.14.0","platform":"linux","release":"5.11.13-arch1-1","cpus":"11th Gen Intel(R) Core(TM) i5-1135G7 @ 2.40GHz","arch":"x64","ci":false,"ciName":null,"docker":false,"termProgram":"tmux","isTTY":true},"componentVersion":"2.2.0","dbEngine":"redux","features":[],"repositoryId":"git:922532e2e902cbe3de09d9d12bd4063122c43df9ebf3a0f55b11b7f6fdc5ebee","repositoryData":{"provider":"3aeb002460381c6f258e8395d3026f571f0d9a76488dcd837639b13aed316560","owner":"4802165693016e28eb2e0a119d108943ea3e918af9b11e5caa073607c0bb8edd","name":"f79ad80b94f6b8e16bdcc8c42e023f768754b0b83db96253b4132d3f12081a13"}}
{"installedGatsbyVersion":"3.2.1","gatsbyCliVersion":"-0.0.0","name":"copy gatsby files","duration":25,"siteHash":"a887cd0a0718944fe3448416e45fdd3a","eventType":"CLI_COMMAND_ACTIVITY_DURATION","sessionId":"f2c5a479-a8ca-408b-a4ef-492bda8591f9","time":"2021-04-07T22:39:46.078Z","machineId":"c48bc250-dd69-4dcb-87c6-aa73be888b8a","componentId":"gatsby-cli","osInformation":{"nodeVersion":"v15.14.0","platform":"linux","release":"5.11.13-arch1-1","cpus":"11th Gen Intel(R) Core(TM) i5-1135G7 @ 2.40GHz","arch":"x64","ci":false,"ciName":null,"docker":false,"termProgram":"tmux","isTTY":true},"componentVersion":"2.2.0","dbEngine":"redux","features":[],"repositoryId":"git:922532e2e902cbe3de09d9d12bd4063122c43df9ebf3a0f55b11b7f6fdc5ebee","repositoryData":{"provider":"3aeb002460381c6f258e8395d3026f571f0d9a76488dcd837639b13aed316560","owner":"4802165693016e28eb2e0a119d108943ea3e918af9b11e5caa073607c0bb8edd","name":"f79ad80b94f6b8e16bdcc8c42e023f768754b0b83db96253b4132d3f12081a13"}}
{"installedGatsbyVersion":"3.2.1","gatsbyCliVersion":"-0.0.0","name":"onPreBootstrap","duration":10,"siteHash":"a887cd0a0718944fe3448416e45fdd3a","eventType":"CLI_COMMAND_ACTIVITY_DURATION","sessionId":"f2c5a479-a8ca-408b-a4ef-492bda8591f9","time":"2021-04-07T22:39:46.089Z","machineId":"c48bc250-dd69-4dcb-87c6-aa73be888b8a","componentId":"gatsby-cli","osInformation":{"nodeVersion":"v15.14.0","platform":"linux","release":"5.11.13-arch1-1","cpus":"11th Gen Intel(R) Core(TM) i5-1135G7 @ 2.40GHz","arch":"x64","ci":false,"ciName":null,"docker":false,"termProgram":"tmux","isTTY":true},"componentVersion":"2.2.0","dbEngine":"redux","features":[],"repositoryId":"git:922532e2e902cbe3de09d9d12bd4063122c43df9ebf3a0f55b11b7f6fdc5ebee","repositoryData":{"provider":"3aeb002460381c6f258e8395d3026f571f0d9a76488dcd837639b13aed316560","owner":"4802165693016e28eb2e0a119d108943ea3e918af9b11e5caa073607c0bb8edd","name":"f79ad80b94f6b8e16bdcc8c42e023f768754b0b83db96253b4132d3f12081a13"}}
{"installedGatsbyVersion":"3.2.1","gatsbyCliVersion":"-0.0.0","name":"createSchemaCustomization","duration":5,"siteHash":"a887cd0a0718944fe3448416e45fdd3a","eventType":"CLI_COMMAND_ACTIVITY_DURATION","sessionId":"f2c5a479-a8ca-408b-a4ef-492bda8591f9","time":"2021-04-07T22:39:46.140Z","machineId":"c48bc250-dd69-4dcb-87c6-aa73be888b8a","componentId":"gatsby-cli","osInformation":{"nodeVersion":"v15.14.0","platform":"linux","release":"5.11.13-arch1-1","cpus":"11th Gen Intel(R) Core(TM) i5-1135G7 @ 2.40GHz","arch":"x64","ci":false,"ciName":null,"docker":false,"termProgram":"tmux","isTTY":true},"componentVersion":"2.2.0","dbEngine":"redux","features":[],"repositoryId":"git:922532e2e902cbe3de09d9d12bd4063122c43df9ebf3a0f55b11b7f6fdc5ebee","repositoryData":{"provider":"3aeb002460381c6f258e8395d3026f571f0d9a76488dcd837639b13aed316560","owner":"4802165693016e28eb2e0a119d108943ea3e918af9b11e5caa073607c0bb8edd","name":"f79ad80b94f6b8e16bdcc8c42e023f768754b0b83db96253b4132d3f12081a13"}}
{"installedGatsbyVersion":"3.2.1","gatsbyCliVersion":"-0.0.0","pluginName":"internal-data-bridge@1.0.0","siteHash":"a887cd0a0718944fe3448416e45fdd3a","eventType":"CLI_COMMAND_CREATE_NODE","sessionId":"f2c5a479-a8ca-408b-a4ef-492bda8591f9","time":"2021-04-07T22:39:46.147Z","machineId":"c48bc250-dd69-4dcb-87c6-aa73be888b8a","componentId":"gatsby-cli","osInformation":{"nodeVersion":"v15.14.0","platform":"linux","release":"5.11.13-arch1-1","cpus":"11th Gen Intel(R) Core(TM) i5-1135G7 @ 2.40GHz","arch":"x64","ci":false,"ciName":null,"docker":false,"termProgram":"tmux","isTTY":true},"componentVersion":"2.2.0","dbEngine":"redux","features":[],"repositoryId":"git:922532e2e902cbe3de09d9d12bd4063122c43df9ebf3a0f55b11b7f6fdc5ebee","repositoryData":{"provider":"3aeb002460381c6f258e8395d3026f571f0d9a76488dcd837639b13aed316560","owner":"4802165693016e28eb2e0a119d108943ea3e918af9b11e5caa073607c0bb8edd","name":"f79ad80b94f6b8e16bdcc8c42e023f768754b0b83db96253b4132d3f12081a13"}}
{"installedGatsbyVersion":"3.2.1","gatsbyCliVersion":"-0.0.0","pluginName":"gatsby-source-filesystem@3.2.0","siteHash":"a887cd0a0718944fe3448416e45fdd3a","eventType":"CLI_COMMAND_CREATE_NODE","sessionId":"f2c5a479-a8ca-408b-a4ef-492bda8591f9","time":"2021-04-07T22:39:46.184Z","machineId":"c48bc250-dd69-4dcb-87c6-aa73be888b8a","componentId":"gatsby-cli","osInformation":{"nodeVersion":"v15.14.0","platform":"linux","release":"5.11.13-arch1-1","cpus":"11th Gen Intel(R) Core(TM) i5-1135G7 @ 2.40GHz","arch":"x64","ci":false,"ciName":null,"docker":false,"termProgram":"tmux","isTTY":true},"componentVersion":"2.2.0","dbEngine":"redux","features":[],"repositoryId":"git:922532e2e902cbe3de09d9d12bd4063122c43df9ebf3a0f55b11b7f6fdc5ebee","repositoryData":{"provider":"3aeb002460381c6f258e8395d3026f571f0d9a76488dcd837639b13aed316560","owner":"4802165693016e28eb2e0a119d108943ea3e918af9b11e5caa073607c0bb8edd","name":"f79ad80b94f6b8e16bdcc8c42e023f768754b0b83db96253b4132d3f12081a13"}}
{"installedGatsbyVersion":"3.2.1","gatsbyCliVersion":"-0.0.0","pluginName":"gatsby-transformer-sharp@3.2.0","siteHash":"a887cd0a0718944fe3448416e45fdd3a","eventType":"CLI_COMMAND_CREATE_NODE","sessionId":"f2c5a479-a8ca-408b-a4ef-492bda8591f9","time":"2021-04-07T22:39:46.190Z","machineId":"c48bc250-dd69-4dcb-87c6-aa73be888b8a","componentId":"gatsby-cli","osInformation":{"nodeVersion":"v15.14.0","platform":"linux","release":"5.11.13-arch1-1","cpus":"11th Gen Intel(R) Core(TM) i5-1135G7 @ 2.40GHz","arch":"x64","ci":false,"ciName":null,"docker":false,"termProgram":"tmux","isTTY":true},"componentVersion":"2.2.0","dbEngine":"redux","features":[],"repositoryId":"git:922532e2e902cbe3de09d9d12bd4063122c43df9ebf3a0f55b11b7f6fdc5ebee","repositoryData":{"provider":"3aeb002460381c6f258e8395d3026f571f0d9a76488dcd837639b13aed316560","owner":"4802165693016e28eb2e0a119d108943ea3e918af9b11e5caa073607c0bb8edd","name":"f79ad80b94f6b8e16bdcc8c42e023f768754b0b83db96253b4132d3f12081a13"}}
{"installedGatsbyVersion":"3.2.1","gatsbyCliVersion":"-0.0.0","name":"Checking for changed pages","duration":1,"siteHash":"a887cd0a0718944fe3448416e45fdd3a","eventType":"CLI_COMMAND_ACTIVITY_DURATION","sessionId":"f2c5a479-a8ca-408b-a4ef-492bda8591f9","time":"2021-04-07T22:39:46.201Z","machineId":"c48bc250-dd69-4dcb-87c6-aa73be888b8a","componentId":"gatsby-cli","osInformation":{"nodeVersion":"v15.14.0","platform":"linux","release":"5.11.13-arch1-1","cpus":"11th Gen Intel(R) Core(TM) i5-1135G7 @ 2.40GHz","arch":"x64","ci":false,"ciName":null,"docker":false,"termProgram":"tmux","isTTY":true},"componentVersion":"2.2.0","dbEngine":"redux","features":[],"repositoryId":"git:922532e2e902cbe3de09d9d12bd4063122c43df9ebf3a0f55b11b7f6fdc5ebee","repositoryData":{"provider":"3aeb002460381c6f258e8395d3026f571f0d9a76488dcd837639b13aed316560","owner":"4802165693016e28eb2e0a119d108943ea3e918af9b11e5caa073607c0bb8edd","name":"f79ad80b94f6b8e16bdcc8c42e023f768754b0b83db96253b4132d3f12081a13"}}
{"installedGatsbyVersion":"3.2.1","gatsbyCliVersion":"-0.0.0","name":"source and transform nodes","duration":60,"siteHash":"a887cd0a0718944fe3448416e45fdd3a","eventType":"CLI_COMMAND_ACTIVITY_DURATION","sessionId":"f2c5a479-a8ca-408b-a4ef-492bda8591f9","time":"2021-04-07T22:39:46.203Z","machineId":"c48bc250-dd69-4dcb-87c6-aa73be888b8a","componentId":"gatsby-cli","osInformation":{"nodeVersion":"v15.14.0","platform":"linux","release":"5.11.13-arch1-1","cpus":"11th Gen Intel(R) Core(TM) i5-1135G7 @ 2.40GHz","arch":"x64","ci":false,"ciName":null,"docker":false,"termProgram":"tmux","isTTY":true},"componentVersion":"2.2.0","dbEngine":"redux","features":[],"repositoryId":"git:922532e2e902cbe3de09d9d12bd4063122c43df9ebf3a0f55b11b7f6fdc5ebee","repositoryData":{"provider":"3aeb002460381c6f258e8395d3026f571f0d9a76488dcd837639b13aed316560","owner":"4802165693016e28eb2e0a119d108943ea3e918af9b11e5caa073607c0bb8edd","name":"f79ad80b94f6b8e16bdcc8c42e023f768754b0b83db96253b4132d3f12081a13"}}
{"installedGatsbyVersion":"3.2.1","gatsbyCliVersion":"-0.0.0","name":"Add explicit types","duration":10,"siteHash":"a887cd0a0718944fe3448416e45fdd3a","eventType":"CLI_COMMAND_ACTIVITY_DURATION","sessionId":"f2c5a479-a8ca-408b-a4ef-492bda8591f9","time":"2021-04-07T22:39:46.235Z","machineId":"c48bc250-dd69-4dcb-87c6-aa73be888b8a","componentId":"gatsby-cli","osInformation":{"nodeVersion":"v15.14.0","platform":"linux","release":"5.11.13-arch1-1","cpus":"11th Gen Intel(R) Core(TM) i5-1135G7 @ 2.40GHz","arch":"x64","ci":false,"ciName":null,"docker":false,"termProgram":"tmux","isTTY":true},"componentVersion":"2.2.0","dbEngine":"redux","features":[],"repositoryId":"git:922532e2e902cbe3de09d9d12bd4063122c43df9ebf3a0f55b11b7f6fdc5ebee","repositoryData":{"provider":"3aeb002460381c6f258e8395d3026f571f0d9a76488dcd837639b13aed316560","owner":"4802165693016e28eb2e0a119d108943ea3e918af9b11e5caa073607c0bb8edd","name":"f79ad80b94f6b8e16bdcc8c42e023f768754b0b83db96253b4132d3f12081a13"}}
{"installedGatsbyVersion":"3.2.1","gatsbyCliVersion":"-0.0.0","name":"Add inferred types","duration":92,"siteHash":"a887cd0a0718944fe3448416e45fdd3a","eventType":"CLI_COMMAND_ACTIVITY_DURATION","sessionId":"f2c5a479-a8ca-408b-a4ef-492bda8591f9","time":"2021-04-07T22:39:46.328Z","machineId":"c48bc250-dd69-4dcb-87c6-aa73be888b8a","componentId":"gatsby-cli","osInformation":{"nodeVersion":"v15.14.0","platform":"linux","release":"5.11.13-arch1-1","cpus":"11th Gen Intel(R) Core(TM) i5-1135G7 @ 2.40GHz","arch":"x64","ci":false,"ciName":null,"docker":false,"termProgram":"tmux","isTTY":true},"componentVersion":"2.2.0","dbEngine":"redux","features":[],"repositoryId":"git:922532e2e902cbe3de09d9d12bd4063122c43df9ebf3a0f55b11b7f6fdc5ebee","repositoryData":{"provider":"3aeb002460381c6f258e8395d3026f571f0d9a76488dcd837639b13aed316560","owner":"4802165693016e28eb2e0a119d108943ea3e918af9b11e5caa073607c0bb8edd","name":"f79ad80b94f6b8e16bdcc8c42e023f768754b0b83db96253b4132d3f12081a13"}}
{"installedGatsbyVersion":"3.2.1","gatsbyCliVersion":"-0.0.0","name":"Processing types","duration":115,"siteHash":"a887cd0a0718944fe3448416e45fdd3a","eventType":"CLI_COMMAND_ACTIVITY_DURATION","sessionId":"f2c5a479-a8ca-408b-a4ef-492bda8591f9","time":"2021-04-07T22:39:46.443Z","machineId":"c48bc250-dd69-4dcb-87c6-aa73be888b8a","componentId":"gatsby-cli","osInformation":{"nodeVersion":"v15.14.0","platform":"linux","release":"5.11.13-arch1-1","cpus":"11th Gen Intel(R) Core(TM) i5-1135G7 @ 2.40GHz","arch":"x64","ci":false,"ciName":null,"docker":false,"termProgram":"tmux","isTTY":true},"componentVersion":"2.2.0","dbEngine":"redux","features":[],"repositoryId":"git:922532e2e902cbe3de09d9d12bd4063122c43df9ebf3a0f55b11b7f6fdc5ebee","repositoryData":{"provider":"3aeb002460381c6f258e8395d3026f571f0d9a76488dcd837639b13aed316560","owner":"4802165693016e28eb2e0a119d108943ea3e918af9b11e5caa073607c0bb8edd","name":"f79ad80b94f6b8e16bdcc8c42e023f768754b0b83db96253b4132d3f12081a13"}}
{"installedGatsbyVersion":"3.2.1","gatsbyCliVersion":"-0.0.0","name":"building schema","duration":269,"siteHash":"a887cd0a0718944fe3448416e45fdd3a","eventType":"CLI_COMMAND_ACTIVITY_DURATION","sessionId":"f2c5a479-a8ca-408b-a4ef-492bda8591f9","time":"2021-04-07T22:39:46.474Z","machineId":"c48bc250-dd69-4dcb-87c6-aa73be888b8a","componentId":"gatsby-cli","osInformation":{"nodeVersion":"v15.14.0","platform":"linux","release":"5.11.13-arch1-1","cpus":"11th Gen Intel(R) Core(TM) i5-1135G7 @ 2.40GHz","arch":"x64","ci":false,"ciName":null,"docker":false,"termProgram":"tmux","isTTY":true},"componentVersion":"2.2.0","dbEngine":"redux","features":[],"repositoryId":"git:922532e2e902cbe3de09d9d12bd4063122c43df9ebf3a0f55b11b7f6fdc5ebee","repositoryData":{"provider":"3aeb002460381c6f258e8395d3026f571f0d9a76488dcd837639b13aed316560","owner":"4802165693016e28eb2e0a119d108943ea3e918af9b11e5caa073607c0bb8edd","name":"f79ad80b94f6b8e16bdcc8c42e023f768754b0b83db96253b4132d3f12081a13"}}
{"installedGatsbyVersion":"3.2.1","gatsbyCliVersion":"-0.0.0","name":"createPages","duration":3,"siteHash":"a887cd0a0718944fe3448416e45fdd3a","eventType":"CLI_COMMAND_ACTIVITY_DURATION","sessionId":"f2c5a479-a8ca-408b-a4ef-492bda8591f9","time":"2021-04-07T22:39:46.479Z","machineId":"c48bc250-dd69-4dcb-87c6-aa73be888b8a","componentId":"gatsby-cli","osInformation":{"nodeVersion":"v15.14.0","platform":"linux","release":"5.11.13-arch1-1","cpus":"11th Gen Intel(R) Core(TM) i5-1135G7 @ 2.40GHz","arch":"x64","ci":false,"ciName":null,"docker":false,"termProgram":"tmux","isTTY":true},"componentVersion":"2.2.0","dbEngine":"redux","features":[],"repositoryId":"git:922532e2e902cbe3de09d9d12bd4063122c43df9ebf3a0f55b11b7f6fdc5ebee","repositoryData":{"provider":"3aeb002460381c6f258e8395d3026f571f0d9a76488dcd837639b13aed316560","owner":"4802165693016e28eb2e0a119d108943ea3e918af9b11e5caa073607c0bb8edd","name":"f79ad80b94f6b8e16bdcc8c42e023f768754b0b83db96253b4132d3f12081a13"}}
{"installedGatsbyVersion":"3.2.1","gatsbyCliVersion":"-0.0.0","name":"Checking for changed pages","duration":1,"siteHash":"a887cd0a0718944fe3448416e45fdd3a","eventType":"CLI_COMMAND_ACTIVITY_DURATION","sessionId":"f2c5a479-a8ca-408b-a4ef-492bda8591f9","time":"2021-04-07T22:39:46.481Z","machineId":"c48bc250-dd69-4dcb-87c6-aa73be888b8a","componentId":"gatsby-cli","osInformation":{"nodeVersion":"v15.14.0","platform":"linux","release":"5.11.13-arch1-1","cpus":"11th Gen Intel(R) Core(TM) i5-1135G7 @ 2.40GHz","arch":"x64","ci":false,"ciName":null,"docker":false,"termProgram":"tmux","isTTY":true},"componentVersion":"2.2.0","dbEngine":"redux","features":[],"repositoryId":"git:922532e2e902cbe3de09d9d12bd4063122c43df9ebf3a0f55b11b7f6fdc5ebee","repositoryData":{"provider":"3aeb002460381c6f258e8395d3026f571f0d9a76488dcd837639b13aed316560","owner":"4802165693016e28eb2e0a119d108943ea3e918af9b11e5caa073607c0bb8edd","name":"f79ad80b94f6b8e16bdcc8c42e023f768754b0b83db96253b4132d3f12081a13"}}
{"installedGatsbyVersion":"3.2.1","gatsbyCliVersion":"-0.0.0","name":"createPagesStatefully","duration":38,"siteHash":"a887cd0a0718944fe3448416e45fdd3a","eventType":"CLI_COMMAND_ACTIVITY_DURATION","sessionId":"f2c5a479-a8ca-408b-a4ef-492bda8591f9","time":"2021-04-07T22:39:46.521Z","machineId":"c48bc250-dd69-4dcb-87c6-aa73be888b8a","componentId":"gatsby-cli","osInformation":{"nodeVersion":"v15.14.0","platform":"linux","release":"5.11.13-arch1-1","cpus":"11th Gen Intel(R) Core(TM) i5-1135G7 @ 2.40GHz","arch":"x64","ci":false,"ciName":null,"docker":false,"termProgram":"tmux","isTTY":true},"componentVersion":"2.2.0","dbEngine":"redux","features":[],"repositoryId":"git:922532e2e902cbe3de09d9d12bd4063122c43df9ebf3a0f55b11b7f6fdc5ebee","repositoryData":{"provider":"3aeb002460381c6f258e8395d3026f571f0d9a76488dcd837639b13aed316560","owner":"4802165693016e28eb2e0a119d108943ea3e918af9b11e5caa073607c0bb8edd","name":"f79ad80b94f6b8e16bdcc8c42e023f768754b0b83db96253b4132d3f12081a13"}}
{"installedGatsbyVersion":"3.2.1","gatsbyCliVersion":"-0.0.0","name":"update schema","duration":40,"siteHash":"a887cd0a0718944fe3448416e45fdd3a","eventType":"CLI_COMMAND_ACTIVITY_DURATION","sessionId":"f2c5a479-a8ca-408b-a4ef-492bda8591f9","time":"2021-04-07T22:39:46.563Z","machineId":"c48bc250-dd69-4dcb-87c6-aa73be888b8a","componentId":"gatsby-cli","osInformation":{"nodeVersion":"v15.14.0","platform":"linux","release":"5.11.13-arch1-1","cpus":"11th Gen Intel(R) Core(TM) i5-1135G7 @ 2.40GHz","arch":"x64","ci":false,"ciName":null,"docker":false,"termProgram":"tmux","isTTY":true},"componentVersion":"2.2.0","dbEngine":"redux","features":[],"repositoryId":"git:922532e2e902cbe3de09d9d12bd4063122c43df9ebf3a0f55b11b7f6fdc5ebee","repositoryData":{"provider":"3aeb002460381c6f258e8395d3026f571f0d9a76488dcd837639b13aed316560","owner":"4802165693016e28eb2e0a119d108943ea3e918af9b11e5caa073607c0bb8edd","name":"f79ad80b94f6b8e16bdcc8c42e023f768754b0b83db96253b4132d3f12081a13"}}
{"installedGatsbyVersion":"3.2.1","gatsbyCliVersion":"-0.0.0","name":"write out redirect data","duration":1,"siteHash":"a887cd0a0718944fe3448416e45fdd3a","eventType":"CLI_COMMAND_ACTIVITY_DURATION","sessionId":"f2c5a479-a8ca-408b-a4ef-492bda8591f9","time":"2021-04-07T22:39:46.566Z","machineId":"c48bc250-dd69-4dcb-87c6-aa73be888b8a","componentId":"gatsby-cli","osInformation":{"nodeVersion":"v15.14.0","platform":"linux","release":"5.11.13-arch1-1","cpus":"11th Gen Intel(R) Core(TM) i5-1135G7 @ 2.40GHz","arch":"x64","ci":false,"ciName":null,"docker":false,"termProgram":"tmux","isTTY":true},"componentVersion":"2.2.0","dbEngine":"redux","features":[],"repositoryId":"git:922532e2e902cbe3de09d9d12bd4063122c43df9ebf3a0f55b11b7f6fdc5ebee","repositoryData":{"provider":"3aeb002460381c6f258e8395d3026f571f0d9a76488dcd837639b13aed316560","owner":"4802165693016e28eb2e0a119d108943ea3e918af9b11e5caa073607c0bb8edd","name":"f79ad80b94f6b8e16bdcc8c42e023f768754b0b83db96253b4132d3f12081a13"}}
{"installedGatsbyVersion":"3.2.1","gatsbyCliVersion":"-0.0.0","name":"Build manifest and related icons","duration":96,"siteHash":"a887cd0a0718944fe3448416e45fdd3a","eventType":"CLI_COMMAND_ACTIVITY_DURATION","sessionId":"f2c5a479-a8ca-408b-a4ef-492bda8591f9","time":"2021-04-07T22:39:46.666Z","machineId":"c48bc250-dd69-4dcb-87c6-aa73be888b8a","componentId":"gatsby-cli","osInformation":{"nodeVersion":"v15.14.0","platform":"linux","release":"5.11.13-arch1-1","cpus":"11th Gen Intel(R) Core(TM) i5-1135G7 @ 2.40GHz","arch":"x64","ci":false,"ciName":null,"docker":false,"termProgram":"tmux","isTTY":true},"componentVersion":"2.2.0","dbEngine":"redux","features":[],"repositoryId":"git:922532e2e902cbe3de09d9d12bd4063122c43df9ebf3a0f55b11b7f6fdc5ebee","repositoryData":{"provider":"3aeb002460381c6f258e8395d3026f571f0d9a76488dcd837639b13aed316560","owner":"4802165693016e28eb2e0a119d108943ea3e918af9b11e5caa073607c0bb8edd","name":"f79ad80b94f6b8e16bdcc8c42e023f768754b0b83db96253b4132d3f12081a13"}}
{"installedGatsbyVersion":"3.2.1","gatsbyCliVersion":"-0.0.0","name":"onPostBootstrap","duration":100,"siteHash":"a887cd0a0718944fe3448416e45fdd3a","eventType":"CLI_COMMAND_ACTIVITY_DURATION","sessionId":"f2c5a479-a8ca-408b-a4ef-492bda8591f9","time":"2021-04-07T22:39:46.668Z","machineId":"c48bc250-dd69-4dcb-87c6-aa73be888b8a","componentId":"gatsby-cli","osInformation":{"nodeVersion":"v15.14.0","platform":"linux","release":"5.11.13-arch1-1","cpus":"11th Gen Intel(R) Core(TM) i5-1135G7 @ 2.40GHz","arch":"x64","ci":false,"ciName":null,"docker":false,"termProgram":"tmux","isTTY":true},"componentVersion":"2.2.0","dbEngine":"redux","features":[],"repositoryId":"git:922532e2e902cbe3de09d9d12bd4063122c43df9ebf3a0f55b11b7f6fdc5ebee","repositoryData":{"provider":"3aeb002460381c6f258e8395d3026f571f0d9a76488dcd837639b13aed316560","owner":"4802165693016e28eb2e0a119d108943ea3e918af9b11e5caa073607c0bb8edd","name":"f79ad80b94f6b8e16bdcc8c42e023f768754b0b83db96253b4132d3f12081a13"}}
{"installedGatsbyVersion":"3.2.1","gatsbyCliVersion":"-0.0.0","name":"onPreExtractQueries","duration":1,"siteHash":"a887cd0a0718944fe3448416e45fdd3a","eventType":"CLI_COMMAND_ACTIVITY_DURATION","sessionId":"f2c5a479-a8ca-408b-a4ef-492bda8591f9","time":"2021-04-07T22:39:46.676Z","machineId":"c48bc250-dd69-4dcb-87c6-aa73be888b8a","componentId":"gatsby-cli","osInformation":{"nodeVersion":"v15.14.0","platform":"linux","release":"5.11.13-arch1-1","cpus":"11th Gen Intel(R) Core(TM) i5-1135G7 @ 2.40GHz","arch":"x64","ci":false,"ciName":null,"docker":false,"termProgram":"tmux","isTTY":true},"componentVersion":"2.2.0","dbEngine":"redux","features":[],"repositoryId":"git:922532e2e902cbe3de09d9d12bd4063122c43df9ebf3a0f55b11b7f6fdc5ebee","repositoryData":{"provider":"3aeb002460381c6f258e8395d3026f571f0d9a76488dcd837639b13aed316560","owner":"4802165693016e28eb2e0a119d108943ea3e918af9b11e5caa073607c0bb8edd","name":"f79ad80b94f6b8e16bdcc8c42e023f768754b0b83db96253b4132d3f12081a13"}}
{"installedGatsbyVersion":"3.2.1","gatsbyCliVersion":"-0.0.0","name":"extract queries from components","duration":1029,"siteHash":"a887cd0a0718944fe3448416e45fdd3a","eventType":"CLI_COMMAND_ACTIVITY_DURATION","sessionId":"f2c5a479-a8ca-408b-a4ef-492bda8591f9","time":"2021-04-07T22:39:47.706Z","machineId":"c48bc250-dd69-4dcb-87c6-aa73be888b8a","componentId":"gatsby-cli","osInformation":{"nodeVersion":"v15.14.0","platform":"linux","release":"5.11.13-arch1-1","cpus":"11th Gen Intel(R) Core(TM) i5-1135G7 @ 2.40GHz","arch":"x64","ci":false,"ciName":null,"docker":false,"termProgram":"tmux","isTTY":true},"componentVersion":"2.2.0","dbEngine":"redux","features":[],"repositoryId":"git:922532e2e902cbe3de09d9d12bd4063122c43df9ebf3a0f55b11b7f6fdc5ebee","repositoryData":{"provider":"3aeb002460381c6f258e8395d3026f571f0d9a76488dcd837639b13aed316560","owner":"4802165693016e28eb2e0a119d108943ea3e918af9b11e5caa073607c0bb8edd","name":"f79ad80b94f6b8e16bdcc8c42e023f768754b0b83db96253b4132d3f12081a13"}}
{"installedGatsbyVersion":"3.2.1","gatsbyCliVersion":"-0.0.0","name":"write out requires","duration":3,"siteHash":"a887cd0a0718944fe3448416e45fdd3a","eventType":"CLI_COMMAND_ACTIVITY_DURATION","sessionId":"f2c5a479-a8ca-408b-a4ef-492bda8591f9","time":"2021-04-07T22:39:47.769Z","machineId":"c48bc250-dd69-4dcb-87c6-aa73be888b8a","componentId":"gatsby-cli","osInformation":{"nodeVersion":"v15.14.0","platform":"linux","release":"5.11.13-arch1-1","cpus":"11th Gen Intel(R) Core(TM) i5-1135G7 @ 2.40GHz","arch":"x64","ci":false,"ciName":null,"docker":false,"termProgram":"tmux","isTTY":true},"componentVersion":"2.2.0","dbEngine":"redux","features":[],"repositoryId":"git:922532e2e902cbe3de09d9d12bd4063122c43df9ebf3a0f55b11b7f6fdc5ebee","repositoryData":{"provider":"3aeb002460381c6f258e8395d3026f571f0d9a76488dcd837639b13aed316560","owner":"4802165693016e28eb2e0a119d108943ea3e918af9b11e5caa073607c0bb8edd","name":"f79ad80b94f6b8e16bdcc8c42e023f768754b0b83db96253b4132d3f12081a13"}}
{"installedGatsbyVersion":"3.2.1","gatsbyCliVersion":"-0.0.0","name":"run static queries","duration":13,"siteHash":"a887cd0a0718944fe3448416e45fdd3a","eventType":"CLI_COMMAND_ACTIVITY_DURATION","sessionId":"f2c5a479-a8ca-408b-a4ef-492bda8591f9","time":"2021-04-07T22:39:47.784Z","machineId":"c48bc250-dd69-4dcb-87c6-aa73be888b8a","componentId":"gatsby-cli","osInformation":{"nodeVersion":"v15.14.0","platform":"linux","release":"5.11.13-arch1-1","cpus":"11th Gen Intel(R) Core(TM) i5-1135G7 @ 2.40GHz","arch":"x64","ci":false,"ciName":null,"docker":false,"termProgram":"tmux","isTTY":true},"componentVersion":"2.2.0","dbEngine":"redux","features":[],"repositoryId":"git:922532e2e902cbe3de09d9d12bd4063122c43df9ebf3a0f55b11b7f6fdc5ebee","repositoryData":{"provider":"3aeb002460381c6f258e8395d3026f571f0d9a76488dcd837639b13aed316560","owner":"4802165693016e28eb2e0a119d108943ea3e918af9b11e5caa073607c0bb8edd","name":"f79ad80b94f6b8e16bdcc8c42e023f768754b0b83db96253b4132d3f12081a13"}}
{"installedGatsbyVersion":"3.2.1","gatsbyCliVersion":"-0.0.0","name":"run page queries","duration":11,"siteHash":"a887cd0a0718944fe3448416e45fdd3a","eventType":"CLI_COMMAND_ACTIVITY_DURATION","sessionId":"f2c5a479-a8ca-408b-a4ef-492bda8591f9","time":"2021-04-07T22:39:47.798Z","machineId":"c48bc250-dd69-4dcb-87c6-aa73be888b8a","componentId":"gatsby-cli","osInformation":{"nodeVersion":"v15.14.0","platform":"linux","release":"5.11.13-arch1-1","cpus":"11th Gen Intel(R) Core(TM) i5-1135G7 @ 2.40GHz","arch":"x64","ci":false,"ciName":null,"docker":false,"termProgram":"tmux","isTTY":true},"componentVersion":"2.2.0","dbEngine":"redux","features":[],"repositoryId":"git:922532e2e902cbe3de09d9d12bd4063122c43df9ebf3a0f55b11b7f6fdc5ebee","repositoryData":{"provider":"3aeb002460381c6f258e8395d3026f571f0d9a76488dcd837639b13aed316560","owner":"4802165693016e28eb2e0a119d108943ea3e918af9b11e5caa073607c0bb8edd","name":"f79ad80b94f6b8e16bdcc8c42e023f768754b0b83db96253b4132d3f12081a13"}}
{"installedGatsbyVersion":"3.2.1","gatsbyCliVersion":"-0.0.0","name":"building index.html","duration":1742,"siteHash":"a887cd0a0718944fe3448416e45fdd3a","eventType":"CLI_COMMAND_ACTIVITY_DURATION","sessionId":"f2c5a479-a8ca-408b-a4ef-492bda8591f9","time":"2021-04-07T22:39:49.547Z","machineId":"c48bc250-dd69-4dcb-87c6-aa73be888b8a","componentId":"gatsby-cli","osInformation":{"nodeVersion":"v15.14.0","platform":"linux","release":"5.11.13-arch1-1","cpus":"11th Gen Intel(R) Core(TM) i5-1135G7 @ 2.40GHz","arch":"x64","ci":false,"ciName":null,"docker":false,"termProgram":"tmux","isTTY":true},"componentVersion":"2.2.0","dbEngine":"redux","features":[],"repositoryId":"git:922532e2e902cbe3de09d9d12bd4063122c43df9ebf3a0f55b11b7f6fdc5ebee","repositoryData":{"provider":"3aeb002460381c6f258e8395d3026f571f0d9a76488dcd837639b13aed316560","owner":"4802165693016e28eb2e0a119d108943ea3e918af9b11e5caa073607c0bb8edd","name":"f79ad80b94f6b8e16bdcc8c42e023f768754b0b83db96253b4132d3f12081a13"}}
{"installedGatsbyVersion":"3.2.1","gatsbyCliVersion":"-0.0.0","name":"Building development bundle","duration":11973,"siteHash":"a887cd0a0718944fe3448416e45fdd3a","eventType":"CLI_COMMAND_ACTIVITY_DURATION","sessionId":"f2c5a479-a8ca-408b-a4ef-492bda8591f9","time":"2021-04-07T22:39:59.773Z","machineId":"c48bc250-dd69-4dcb-87c6-aa73be888b8a","componentId":"gatsby-cli","osInformation":{"nodeVersion":"v15.14.0","platform":"linux","release":"5.11.13-arch1-1","cpus":"11th Gen Intel(R) Core(TM) i5-1135G7 @ 2.40GHz","arch":"x64","ci":false,"ciName":null,"docker":false,"termProgram":"tmux","isTTY":true},"componentVersion":"2.2.0","dbEngine":"redux","features":[],"repositoryId":"git:922532e2e902cbe3de09d9d12bd4063122c43df9ebf3a0f55b11b7f6fdc5ebee","repositoryData":{"provider":"3aeb002460381c6f258e8395d3026f571f0d9a76488dcd837639b13aed316560","owner":"4802165693016e28eb2e0a119d108943ea3e918af9b11e5caa073607c0bb8edd","name":"f79ad80b94f6b8e16bdcc8c42e023f768754b0b83db96253b4132d3f12081a13"}}
{"installedGatsbyVersion":"3.2.1","gatsbyCliVersion":"-0.0.0","name":"onPreExtractQueries","duration":2,"siteHash":"a887cd0a0718944fe3448416e45fdd3a","eventType":"CLI_COMMAND_ACTIVITY_DURATION","sessionId":"f2c5a479-a8ca-408b-a4ef-492bda8591f9","time":"2021-04-07T22:40:00.048Z","machineId":"c48bc250-dd69-4dcb-87c6-aa73be888b8a","componentId":"gatsby-cli","osInformation":{"nodeVersion":"v15.14.0","platform":"linux","release":"5.11.13-arch1-1","cpus":"11th Gen Intel(R) Core(TM) i5-1135G7 @ 2.40GHz","arch":"x64","ci":false,"ciName":null,"docker":false,"termProgram":"tmux","isTTY":true},"componentVersion":"2.2.0","dbEngine":"redux","features":[],"repositoryId":"git:922532e2e902cbe3de09d9d12bd4063122c43df9ebf3a0f55b11b7f6fdc5ebee","repositoryData":{"provider":"3aeb002460381c6f258e8395d3026f571f0d9a76488dcd837639b13aed316560","owner":"4802165693016e28eb2e0a119d108943ea3e918af9b11e5caa073607c0bb8edd","name":"f79ad80b94f6b8e16bdcc8c42e023f768754b0b83db96253b4132d3f12081a13"}}
{"installedGatsbyVersion":"3.2.1","gatsbyCliVersion":"-0.0.0","name":"extract queries from components","duration":53,"siteHash":"a887cd0a0718944fe3448416e45fdd3a","eventType":"CLI_COMMAND_ACTIVITY_DURATION","sessionId":"f2c5a479-a8ca-408b-a4ef-492bda8591f9","time":"2021-04-07T22:40:00.104Z","machineId":"c48bc250-dd69-4dcb-87c6-aa73be888b8a","componentId":"gatsby-cli","osInformation":{"nodeVersion":"v15.14.0","platform":"linux","release":"5.11.13-arch1-1","cpus":"11th Gen Intel(R) Core(TM) i5-1135G7 @ 2.40GHz","arch":"x64","ci":false,"ciName":null,"docker":false,"termProgram":"tmux","isTTY":true},"componentVersion":"2.2.0","dbEngine":"redux","features":[],"repositoryId":"git:922532e2e902cbe3de09d9d12bd4063122c43df9ebf3a0f55b11b7f6fdc5ebee","repositoryData":{"provider":"3aeb002460381c6f258e8395d3026f571f0d9a76488dcd837639b13aed316560","owner":"4802165693016e28eb2e0a119d108943ea3e918af9b11e5caa073607c0bb8edd","name":"f79ad80b94f6b8e16bdcc8c42e023f768754b0b83db96253b4132d3f12081a13"}}
{"installedGatsbyVersion":"3.2.1","gatsbyCliVersion":"-0.0.0","name":"write out requires","duration":2,"siteHash":"a887cd0a0718944fe3448416e45fdd3a","eventType":"CLI_COMMAND_ACTIVITY_DURATION","sessionId":"f2c5a479-a8ca-408b-a4ef-492bda8591f9","time":"2021-04-07T22:40:00.159Z","machineId":"c48bc250-dd69-4dcb-87c6-aa73be888b8a","componentId":"gatsby-cli","osInformation":{"nodeVersion":"v15.14.0","platform":"linux","release":"5.11.13-arch1-1","cpus":"11th Gen Intel(R) Core(TM) i5-1135G7 @ 2.40GHz","arch":"x64","ci":false,"ciName":null,"docker":false,"termProgram":"tmux","isTTY":true},"componentVersion":"2.2.0","dbEngine":"redux","features":[],"repositoryId":"git:922532e2e902cbe3de09d9d12bd4063122c43df9ebf3a0f55b11b7f6fdc5ebee","repositoryData":{"provider":"3aeb002460381c6f258e8395d3026f571f0d9a76488dcd837639b13aed316560","owner":"4802165693016e28eb2e0a119d108943ea3e918af9b11e5caa073607c0bb8edd","name":"f79ad80b94f6b8e16bdcc8c42e023f768754b0b83db96253b4132d3f12081a13"}}
{"installedGatsbyVersion":"3.2.1","gatsbyCliVersion":"-0.0.0","userAgent":"Mozilla/5.0 (X11; Linux x86_64; rv:88.0) Gecko/20100101 Firefox/88.0","eventType":"CLI_COMMAND_DEVELOP_ACTIVE","sessionId":"f2c5a479-a8ca-408b-a4ef-492bda8591f9","time":"2021-04-07T22:40:00.354Z","machineId":"c48bc250-dd69-4dcb-87c6-aa73be888b8a","componentId":"gatsby-cli","osInformation":{"nodeVersion":"v15.14.0","platform":"linux","release":"5.11.13-arch1-1","cpus":"11th Gen Intel(R) Core(TM) i5-1135G7 @ 2.40GHz","arch":"x64","ci":false,"ciName":null,"docker":false,"termProgram":"tmux","isTTY":true},"componentVersion":"2.2.0","dbEngine":"redux","features":[],"repositoryId":"git:922532e2e902cbe3de09d9d12bd4063122c43df9ebf3a0f55b11b7f6fdc5ebee","repositoryData":{"provider":"3aeb002460381c6f258e8395d3026f571f0d9a76488dcd837639b13aed316560","owner":"4802165693016e28eb2e0a119d108943ea3e918af9b11e5caa073607c0bb8edd","name":"f79ad80b94f6b8e16bdcc8c42e023f768754b0b83db96253b4132d3f12081a13"}}
{"installedGatsbyVersion":"3.2.1","gatsbyCliVersion":"-0.0.0","name":"Re-building development bundle","duration":3593,"siteHash":"a887cd0a0718944fe3448416e45fdd3a","eventType":"CLI_COMMAND_ACTIVITY_DURATION","sessionId":"f2c5a479-a8ca-408b-a4ef-492bda8591f9","time":"2021-04-07T22:40:03.761Z","machineId":"c48bc250-dd69-4dcb-87c6-aa73be888b8a","componentId":"gatsby-cli","osInformation":{"nodeVersion":"v15.14.0","platform":"linux","release":"5.11.13-arch1-1","cpus":"11th Gen Intel(R) Core(TM) i5-1135G7 @ 2.40GHz","arch":"x64","ci":false,"ciName":null,"docker":false,"termProgram":"tmux","isTTY":true},"componentVersion":"2.2.0","dbEngine":"redux","features":[],"repositoryId":"git:922532e2e902cbe3de09d9d12bd4063122c43df9ebf3a0f55b11b7f6fdc5ebee","repositoryData":{"provider":"3aeb002460381c6f258e8395d3026f571f0d9a76488dcd837639b13aed316560","owner":"4802165693016e28eb2e0a119d108943ea3e918af9b11e5caa073607c0bb8edd","name":"f79ad80b94f6b8e16bdcc8c42e023f768754b0b83db96253b4132d3f12081a13"}}
